<?xml version="1.0" encoding="UTF-8" standalone="no"?>
<sfObject detailsLoaded="false" editPermission="false" keyPrefix="0jf" label="Orchestration Work Item" labelPlural="Orchestration Work Items" layoutable="true" n="FlowOrchestrationWorkItem" queryable="true" readPermission="false" retrieveable="true" s="" t="Orchestration Work Item (0jf)" updatable="true">
  <standardActions>
    <sfActionLink modes="ObjectHome FlowOrchestrationWorkItems" n="New"/>
    <sfActionLink modes="View FlowOrchestrationWorkItems" n="Edit" requiresRow="true" s="2"/>
    <sfActionLink modes="View FlowOrchestrationWorkItems" n="Delete" requiresRow="true" s="3"/>
    <sfActionLink lightningActionName="MassChangeOwner" massAction="true" modes="View List all_related_lists" n="ChangeOwnerOne" t="Change Owner"/>
    <sfActionLink modes="View FlowOrchestrationWorkItems" n="ShowMore" t="Show More"/>
    <sfActionLink modes="View FlowOrchestrationWorkItems" n="GoToList" t="Go To List"/>
    <sfActionLink modes="RelatedList" n="PrevPage" t="Previous Page"/>
    <sfActionLink modes="RelatedList" n="NextPage" t="Next Page"/>
  </standardActions>
</sfObject>
